transcriptor/__init__.py
transcriptor/cli.py
transcriptor/constants.py
whisper_transcribe_cli-0.1.2.dist-info/METADATA
whisper_transcribe_cli-0.1.2.dist-info/WHEEL
whisper_transcribe_cli-0.1.2.dist-info/top_level.txt
whisper_transcribe_cli-0.1.2.dist-info/RECORD
